utilspie/__init__.py
utilspie/exceptions.py
utilspie/asyncutils/__init__.py
utilspie/asyncutils/async_utils.py
utilspie/collectionsutils/__init__.py
utilspie/collectionsutils/collections_utils.py
utilspie/fileutils/__init__.py
utilspie/fileutils/file_utils.py
utilspie/importutils/__init__.py
utilspie/importutils/import_utils.py
utilspie/iterutils/__init__.py
utilspie/iterutils/iter_utils.py
utilspie-0.1.0.dist-info/DESCRIPTION.rst
utilspie-0.1.0.dist-info/METADATA
utilspie-0.1.0.dist-info/RECORD
utilspie-0.1.0.dist-info/WHEEL
utilspie-0.1.0.dist-info/metadata.json
utilspie-0.1.0.dist-info/top_level.txt
