Metadata-Version: 2.0
Name: utilspie
Version: 0.1.0
Summary: Python Utilities
Home-page: https://github.com/moin18/utilspie
Author: Moinuddin Quadri
Author-email: moin18@gmail.com
License: MIT
Keywords: utils asyncutils importutils fileutils import file async
Platform: UNKNOWN
Classifier: Development Status :: 4 - Beta
Classifier: Intended Audience :: Developers
Classifier: Topic :: Software Development :: Libraries
Classifier: License :: OSI Approved :: MIT License
Classifier: Programming Language :: Python :: 2
Classifier: Programming Language :: Python :: 2.6
Classifier: Programming Language :: Python :: 2.7
Classifier: Programming Language :: Python :: 3
Classifier: Programming Language :: Python :: 3.3
Classifier: Programming Language :: Python :: 3.4
Classifier: Programming Language :: Python :: 3.5
